{
  "username": "cts-2007003",
  "display_name": "Vishnu",
  "team": "Magicals",
  "total_lines_written": 4755,
  "total_ai_lines": 1556,
  "history": [
    {
      "date": "2026-04-04",
      "total": 86,
      "ai": 36
    },
    {
      "date": "2026-04-06",
      "total": 466,
      "ai": 0
    },
    {
      "date": "2026-04-07",
      "total": 411,
      "ai": 66
    },
    {
      "date": "2026-04-10",
      "total": 241,
      "ai": 48
    },
    {
      "date": "2026-04-13",
      "total": 1857,
      "ai": 140
    },
    {
      "date": "2026-04-14",
      "total": 634,
      "ai": 524
    },
    {
      "date": "2026-04-15",
      "total": 687,
      "ai": 507
    },
    {
      "date": "2026-04-16",
      "total": 373,
      "ai": 235
    }
  ],
  "last_updated": "2026-04-16T18:32:28.8800618+05:30"
}